cyberfusion/Nodechup/CLI.py
cyberfusion/Nodechup/__init__.py
cyberfusion/Nodechup/nodejs.py
cyberfusion/Nodechup/utilities.py
nodechup-1.2.2.1.dist-info/METADATA
nodechup-1.2.2.1.dist-info/WHEEL
nodechup-1.2.2.1.dist-info/entry_points.txt
nodechup-1.2.2.1.dist-info/top_level.txt
nodechup-1.2.2.1.dist-info/RECORD
