Metadata-Version: 2.1
Name: nodechup
Version: 1.2.2.1
Summary: Use nodechup to install multiple Node.js versions.
Author-email: Cyberfusion <support@cyberfusion.io>
Project-URL: Source, https://github.com/CyberfusionIO/nodechup
Requires-Dist: docopt ==0.6.2
Requires-Dist: schema ==0.7.7
Requires-Dist: requests ==2.32.3
